simple_icd_10_cm/__init__.py
simple_icd_10_cm/simple_icd_10_cm.py
simple_icd_10_cm/data/__init__.py
simple_icd_10_cm/data/code-list-April-2025.txt
simple_icd_10_cm/data/icd10cm-tabular-April-2025.xml
simple_icd_10_cm-1.4.0.dist-info/licenses/LICENSE
simple_icd_10_cm-1.4.0.dist-info/METADATA
simple_icd_10_cm-1.4.0.dist-info/WHEEL
simple_icd_10_cm-1.4.0.dist-info/top_level.txt
simple_icd_10_cm-1.4.0.dist-info/RECORD
