Metadata-Version: 2.4
Name: simple_icd_10_cm
Version: 1.4.0
Summary: A simple python library for ICD-10-CM codes
Home-page: https://github.com/StefanoTrv/simple_icd_10_CM
Author: Stefano Travasci
Author-email: stefanotravasci@gmail.com
Keywords: ICD-10-CM ICD-10 icd 10 CM codes clinical modification
Classifier: Programming Language :: Python :: 3
Classifier: License :: OSI Approved :: MIT License
Classifier: Operating System :: OS Independent
Requires-Python: >=3.9
License-File: LICENSE
Dynamic: author
Dynamic: author-email
Dynamic: classifier
Dynamic: description
Dynamic: description-content-type
Dynamic: home-page
Dynamic: keywords
Dynamic: license-file
Dynamic: requires-python
Dynamic: summary
